{ "time": "2023-11-23 14:57:11.9518", "level": "WARN", "app": "dotnet", "thread": "55", "message": {"SQL":"\nSELECT\n\t\"BulkEmail\".\"Id\",\n\t\"BulkEmail\".\"CategoryId\",\n\t\"BulkEmail\".\"SendStartDate\",\n\t\"BulkEmail\".\"StatusId\",\n\t\"BulkEmail\".\"LaunchOptionId\"\nFROM\n\t\"public\".\"BulkEmail\"\n\tINNER JOIN \"public\".\"SendingEmailProgress\" ON (\"SendingEmailProgress\".\"BulkEmailId\" = \"BulkEmail\".\"Id\")\n\tLEFT OUTER JOIN \"public\".\"Campaign\" ON (\"Campaign\".\"Id\" = \"BulkEmail\".\"CampaignId\")\nWHERE\n\t\"BulkEmail\".\"StatusId\" IN (@P1, @P2, @P3, @P4, @P5)\n\tAND \"Campaign\".\"CampaignSchemaUId\" IS NULL\n\tAND \"SendingEmailProgress\".\"SendStartDate\" < @P6\n\tAND \"SendingEmailProgress\".\"SendStartDate\" > @P7","ErrorMessage":"42703: column SendingEmailProgress.SendStartDate does not exist","Parameters":[]} }
{ "time": "2023-11-23 15:02:00.2366", "level": "WARN", "app": "dotnet", "thread": "48", "message": {"SQL":"\nSELECT\n\t\"BulkEmail\".\"Id\",\n\t\"BulkEmail\".\"CategoryId\",\n\t\"BulkEmail\".\"SendStartDate\",\n\t\"BulkEmail\".\"StatusId\",\n\t\"BulkEmail\".\"LaunchOptionId\"\nFROM\n\t\"public\".\"BulkEmail\"\n\tINNER JOIN \"public\".\"SendingEmailProgress\" ON (\"SendingEmailProgress\".\"BulkEmailId\" = \"BulkEmail\".\"Id\")\n\tLEFT OUTER JOIN \"public\".\"Campaign\" ON (\"Campaign\".\"Id\" = \"BulkEmail\".\"CampaignId\")\nWHERE\n\t\"BulkEmail\".\"StatusId\" IN (@P1, @P2, @P3, @P4, @P5)\n\tAND \"Campaign\".\"CampaignSchemaUId\" IS NULL\n\tAND \"SendingEmailProgress\".\"SendStartDate\" < @P6\n\tAND \"SendingEmailProgress\".\"SendStartDate\" > @P7","ErrorMessage":"42703: column SendingEmailProgress.SendStartDate does not exist","Parameters":[]} }
{ "time": "2023-11-23 15:07:00.2662", "level": "WARN", "app": "dotnet", "thread": "141", "message": {"SQL":"\nSELECT\n\t\"BulkEmail\".\"Id\",\n\t\"BulkEmail\".\"CategoryId\",\n\t\"BulkEmail\".\"SendStartDate\",\n\t\"BulkEmail\".\"StatusId\",\n\t\"BulkEmail\".\"LaunchOptionId\"\nFROM\n\t\"public\".\"BulkEmail\"\n\tINNER JOIN \"public\".\"SendingEmailProgress\" ON (\"SendingEmailProgress\".\"BulkEmailId\" = \"BulkEmail\".\"Id\")\n\tLEFT OUTER JOIN \"public\".\"Campaign\" ON (\"Campaign\".\"Id\" = \"BulkEmail\".\"CampaignId\")\nWHERE\n\t\"BulkEmail\".\"StatusId\" IN (@P1, @P2, @P3, @P4, @P5)\n\tAND \"Campaign\".\"CampaignSchemaUId\" IS NULL\n\tAND \"SendingEmailProgress\".\"SendStartDate\" < @P6\n\tAND \"SendingEmailProgress\".\"SendStartDate\" > @P7","ErrorMessage":"42703: column SendingEmailProgress.SendStartDate does not exist","Parameters":[]} }
{ "time": "2023-11-23 15:12:00.2509", "level": "WARN", "app": "dotnet", "thread": "140", "message": {"SQL":"\nSELECT\n\t\"BulkEmail\".\"Id\",\n\t\"BulkEmail\".\"CategoryId\",\n\t\"BulkEmail\".\"SendStartDate\",\n\t\"BulkEmail\".\"StatusId\",\n\t\"BulkEmail\".\"LaunchOptionId\"\nFROM\n\t\"public\".\"BulkEmail\"\n\tINNER JOIN \"public\".\"SendingEmailProgress\" ON (\"SendingEmailProgress\".\"BulkEmailId\" = \"BulkEmail\".\"Id\")\n\tLEFT OUTER JOIN \"public\".\"Campaign\" ON (\"Campaign\".\"Id\" = \"BulkEmail\".\"CampaignId\")\nWHERE\n\t\"BulkEmail\".\"StatusId\" IN (@P1, @P2, @P3, @P4, @P5)\n\tAND \"Campaign\".\"CampaignSchemaUId\" IS NULL\n\tAND \"SendingEmailProgress\".\"SendStartDate\" < @P6\n\tAND \"SendingEmailProgress\".\"SendStartDate\" > @P7","ErrorMessage":"42703: column SendingEmailProgress.SendStartDate does not exist","Parameters":[]} }
{ "time": "2023-11-23 15:17:00.2657", "level": "WARN", "app": "dotnet", "thread": "108", "message": {"SQL":"\nSELECT\n\t\"BulkEmail\".\"Id\",\n\t\"BulkEmail\".\"CategoryId\",\n\t\"BulkEmail\".\"SendStartDate\",\n\t\"BulkEmail\".\"StatusId\",\n\t\"BulkEmail\".\"LaunchOptionId\"\nFROM\n\t\"public\".\"BulkEmail\"\n\tINNER JOIN \"public\".\"SendingEmailProgress\" ON (\"SendingEmailProgress\".\"BulkEmailId\" = \"BulkEmail\".\"Id\")\n\tLEFT OUTER JOIN \"public\".\"Campaign\" ON (\"Campaign\".\"Id\" = \"BulkEmail\".\"CampaignId\")\nWHERE\n\t\"BulkEmail\".\"StatusId\" IN (@P1, @P2, @P3, @P4, @P5)\n\tAND \"Campaign\".\"CampaignSchemaUId\" IS NULL\n\tAND \"SendingEmailProgress\".\"SendStartDate\" < @P6\n\tAND \"SendingEmailProgress\".\"SendStartDate\" > @P7","ErrorMessage":"42703: column SendingEmailProgress.SendStartDate does not exist","Parameters":[]} }
{ "time": "2023-11-23 15:22:00.2504", "level": "WARN", "app": "dotnet", "thread": "23", "message": {"SQL":"\nSELECT\n\t\"BulkEmail\".\"Id\",\n\t\"BulkEmail\".\"CategoryId\",\n\t\"BulkEmail\".\"SendStartDate\",\n\t\"BulkEmail\".\"StatusId\",\n\t\"BulkEmail\".\"LaunchOptionId\"\nFROM\n\t\"public\".\"BulkEmail\"\n\tINNER JOIN \"public\".\"SendingEmailProgress\" ON (\"SendingEmailProgress\".\"BulkEmailId\" = \"BulkEmail\".\"Id\")\n\tLEFT OUTER JOIN \"public\".\"Campaign\" ON (\"Campaign\".\"Id\" = \"BulkEmail\".\"CampaignId\")\nWHERE\n\t\"BulkEmail\".\"StatusId\" IN (@P1, @P2, @P3, @P4, @P5)\n\tAND \"Campaign\".\"CampaignSchemaUId\" IS NULL\n\tAND \"SendingEmailProgress\".\"SendStartDate\" < @P6\n\tAND \"SendingEmailProgress\".\"SendStartDate\" > @P7","ErrorMessage":"42703: column SendingEmailProgress.SendStartDate does not exist","Parameters":[]} }
{ "time": "2023-11-23 15:27:00.2536", "level": "WARN", "app": "dotnet", "thread": "117", "message": {"SQL":"\nSELECT\n\t\"BulkEmail\".\"Id\",\n\t\"BulkEmail\".\"CategoryId\",\n\t\"BulkEmail\".\"SendStartDate\",\n\t\"BulkEmail\".\"StatusId\",\n\t\"BulkEmail\".\"LaunchOptionId\"\nFROM\n\t\"public\".\"BulkEmail\"\n\tINNER JOIN \"public\".\"SendingEmailProgress\" ON (\"SendingEmailProgress\".\"BulkEmailId\" = \"BulkEmail\".\"Id\")\n\tLEFT OUTER JOIN \"public\".\"Campaign\" ON (\"Campaign\".\"Id\" = \"BulkEmail\".\"CampaignId\")\nWHERE\n\t\"BulkEmail\".\"StatusId\" IN (@P1, @P2, @P3, @P4, @P5)\n\tAND \"Campaign\".\"CampaignSchemaUId\" IS NULL\n\tAND \"SendingEmailProgress\".\"SendStartDate\" < @P6\n\tAND \"SendingEmailProgress\".\"SendStartDate\" > @P7","ErrorMessage":"42703: column SendingEmailProgress.SendStartDate does not exist","Parameters":[]} }
{ "time": "2023-11-23 15:32:00.2470", "level": "WARN", "app": "dotnet", "thread": "115", "message": {"SQL":"\nSELECT\n\t\"BulkEmail\".\"Id\",\n\t\"BulkEmail\".\"CategoryId\",\n\t\"BulkEmail\".\"SendStartDate\",\n\t\"BulkEmail\".\"StatusId\",\n\t\"BulkEmail\".\"LaunchOptionId\"\nFROM\n\t\"public\".\"BulkEmail\"\n\tINNER JOIN \"public\".\"SendingEmailProgress\" ON (\"SendingEmailProgress\".\"BulkEmailId\" = \"BulkEmail\".\"Id\")\n\tLEFT OUTER JOIN \"public\".\"Campaign\" ON (\"Campaign\".\"Id\" = \"BulkEmail\".\"CampaignId\")\nWHERE\n\t\"BulkEmail\".\"StatusId\" IN (@P1, @P2, @P3, @P4, @P5)\n\tAND \"Campaign\".\"CampaignSchemaUId\" IS NULL\n\tAND \"SendingEmailProgress\".\"SendStartDate\" < @P6\n\tAND \"SendingEmailProgress\".\"SendStartDate\" > @P7","ErrorMessage":"42703: column SendingEmailProgress.SendStartDate does not exist","Parameters":[]} }
{ "time": "2023-11-23 15:37:00.2483", "level": "WARN", "app": "dotnet", "thread": "104", "message": {"SQL":"\nSELECT\n\t\"BulkEmail\".\"Id\",\n\t\"BulkEmail\".\"CategoryId\",\n\t\"BulkEmail\".\"SendStartDate\",\n\t\"BulkEmail\".\"StatusId\",\n\t\"BulkEmail\".\"LaunchOptionId\"\nFROM\n\t\"public\".\"BulkEmail\"\n\tINNER JOIN \"public\".\"SendingEmailProgress\" ON (\"SendingEmailProgress\".\"BulkEmailId\" = \"BulkEmail\".\"Id\")\n\tLEFT OUTER JOIN \"public\".\"Campaign\" ON (\"Campaign\".\"Id\" = \"BulkEmail\".\"CampaignId\")\nWHERE\n\t\"BulkEmail\".\"StatusId\" IN (@P1, @P2, @P3, @P4, @P5)\n\tAND \"Campaign\".\"CampaignSchemaUId\" IS NULL\n\tAND \"SendingEmailProgress\".\"SendStartDate\" < @P6\n\tAND \"SendingEmailProgress\".\"SendStartDate\" > @P7","ErrorMessage":"42703: column SendingEmailProgress.SendStartDate does not exist","Parameters":[]} }
{ "time": "2023-11-23 15:42:00.2506", "level": "WARN", "app": "dotnet", "thread": "119", "message": {"SQL":"\nSELECT\n\t\"BulkEmail\".\"Id\",\n\t\"BulkEmail\".\"CategoryId\",\n\t\"BulkEmail\".\"SendStartDate\",\n\t\"BulkEmail\".\"StatusId\",\n\t\"BulkEmail\".\"LaunchOptionId\"\nFROM\n\t\"public\".\"BulkEmail\"\n\tINNER JOIN \"public\".\"SendingEmailProgress\" ON (\"SendingEmailProgress\".\"BulkEmailId\" = \"BulkEmail\".\"Id\")\n\tLEFT OUTER JOIN \"public\".\"Campaign\" ON (\"Campaign\".\"Id\" = \"BulkEmail\".\"CampaignId\")\nWHERE\n\t\"BulkEmail\".\"StatusId\" IN (@P1, @P2, @P3, @P4, @P5)\n\tAND \"Campaign\".\"CampaignSchemaUId\" IS NULL\n\tAND \"SendingEmailProgress\".\"SendStartDate\" < @P6\n\tAND \"SendingEmailProgress\".\"SendStartDate\" > @P7","ErrorMessage":"42703: column SendingEmailProgress.SendStartDate does not exist","Parameters":[]} }
{ "time": "2023-11-23 15:47:00.2675", "level": "WARN", "app": "dotnet", "thread": "26", "message": {"SQL":"\nSELECT\n\t\"BulkEmail\".\"Id\",\n\t\"BulkEmail\".\"CategoryId\",\n\t\"BulkEmail\".\"SendStartDate\",\n\t\"BulkEmail\".\"StatusId\",\n\t\"BulkEmail\".\"LaunchOptionId\"\nFROM\n\t\"public\".\"BulkEmail\"\n\tINNER JOIN \"public\".\"SendingEmailProgress\" ON (\"SendingEmailProgress\".\"BulkEmailId\" = \"BulkEmail\".\"Id\")\n\tLEFT OUTER JOIN \"public\".\"Campaign\" ON (\"Campaign\".\"Id\" = \"BulkEmail\".\"CampaignId\")\nWHERE\n\t\"BulkEmail\".\"StatusId\" IN (@P1, @P2, @P3, @P4, @P5)\n\tAND \"Campaign\".\"CampaignSchemaUId\" IS NULL\n\tAND \"SendingEmailProgress\".\"SendStartDate\" < @P6\n\tAND \"SendingEmailProgress\".\"SendStartDate\" > @P7","ErrorMessage":"42703: column SendingEmailProgress.SendStartDate does not exist","Parameters":[]} }
{ "time": "2023-11-23 15:52:00.2475", "level": "WARN", "app": "dotnet", "thread": "118", "message": {"SQL":"\nSELECT\n\t\"BulkEmail\".\"Id\",\n\t\"BulkEmail\".\"CategoryId\",\n\t\"BulkEmail\".\"SendStartDate\",\n\t\"BulkEmail\".\"StatusId\",\n\t\"BulkEmail\".\"LaunchOptionId\"\nFROM\n\t\"public\".\"BulkEmail\"\n\tINNER JOIN \"public\".\"SendingEmailProgress\" ON (\"SendingEmailProgress\".\"BulkEmailId\" = \"BulkEmail\".\"Id\")\n\tLEFT OUTER JOIN \"public\".\"Campaign\" ON (\"Campaign\".\"Id\" = \"BulkEmail\".\"CampaignId\")\nWHERE\n\t\"BulkEmail\".\"StatusId\" IN (@P1, @P2, @P3, @P4, @P5)\n\tAND \"Campaign\".\"CampaignSchemaUId\" IS NULL\n\tAND \"SendingEmailProgress\".\"SendStartDate\" < @P6\n\tAND \"SendingEmailProgress\".\"SendStartDate\" > @P7","ErrorMessage":"42703: column SendingEmailProgress.SendStartDate does not exist","Parameters":[]} }
{ "time": "2023-11-23 15:57:00.2396", "level": "WARN", "app": "dotnet", "thread": "57", "message": {"SQL":"\nSELECT\n\t\"BulkEmail\".\"Id\",\n\t\"BulkEmail\".\"CategoryId\",\n\t\"BulkEmail\".\"SendStartDate\",\n\t\"BulkEmail\".\"StatusId\",\n\t\"BulkEmail\".\"LaunchOptionId\"\nFROM\n\t\"public\".\"BulkEmail\"\n\tINNER JOIN \"public\".\"SendingEmailProgress\" ON (\"SendingEmailProgress\".\"BulkEmailId\" = \"BulkEmail\".\"Id\")\n\tLEFT OUTER JOIN \"public\".\"Campaign\" ON (\"Campaign\".\"Id\" = \"BulkEmail\".\"CampaignId\")\nWHERE\n\t\"BulkEmail\".\"StatusId\" IN (@P1, @P2, @P3, @P4, @P5)\n\tAND \"Campaign\".\"CampaignSchemaUId\" IS NULL\n\tAND \"SendingEmailProgress\".\"SendStartDate\" < @P6\n\tAND \"SendingEmailProgress\".\"SendStartDate\" > @P7","ErrorMessage":"42703: column SendingEmailProgress.SendStartDate does not exist","Parameters":[]} }
{ "time": "2023-11-23 16:02:00.2297", "level": "WARN", "app": "dotnet", "thread": "90", "message": {"SQL":"\nSELECT\n\t\"BulkEmail\".\"Id\",\n\t\"BulkEmail\".\"CategoryId\",\n\t\"BulkEmail\".\"SendStartDate\",\n\t\"BulkEmail\".\"StatusId\",\n\t\"BulkEmail\".\"LaunchOptionId\"\nFROM\n\t\"public\".\"BulkEmail\"\n\tINNER JOIN \"public\".\"SendingEmailProgress\" ON (\"SendingEmailProgress\".\"BulkEmailId\" = \"BulkEmail\".\"Id\")\n\tLEFT OUTER JOIN \"public\".\"Campaign\" ON (\"Campaign\".\"Id\" = \"BulkEmail\".\"CampaignId\")\nWHERE\n\t\"BulkEmail\".\"StatusId\" IN (@P1, @P2, @P3, @P4, @P5)\n\tAND \"Campaign\".\"CampaignSchemaUId\" IS NULL\n\tAND \"SendingEmailProgress\".\"SendStartDate\" < @P6\n\tAND \"SendingEmailProgress\".\"SendStartDate\" > @P7","ErrorMessage":"42703: column SendingEmailProgress.SendStartDate does not exist","Parameters":[]} }
{ "time": "2023-11-23 16:07:00.4228", "level": "WARN", "app": "dotnet", "thread": "92", "message": {"SQL":"\nSELECT\n\t\"BulkEmail\".\"Id\",\n\t\"BulkEmail\".\"CategoryId\",\n\t\"BulkEmail\".\"SendStartDate\",\n\t\"BulkEmail\".\"StatusId\",\n\t\"BulkEmail\".\"LaunchOptionId\"\nFROM\n\t\"public\".\"BulkEmail\"\n\tINNER JOIN \"public\".\"SendingEmailProgress\" ON (\"SendingEmailProgress\".\"BulkEmailId\" = \"BulkEmail\".\"Id\")\n\tLEFT OUTER JOIN \"public\".\"Campaign\" ON (\"Campaign\".\"Id\" = \"BulkEmail\".\"CampaignId\")\nWHERE\n\t\"BulkEmail\".\"StatusId\" IN (@P1, @P2, @P3, @P4, @P5)\n\tAND \"Campaign\".\"CampaignSchemaUId\" IS NULL\n\tAND \"SendingEmailProgress\".\"SendStartDate\" < @P6\n\tAND \"SendingEmailProgress\".\"SendStartDate\" > @P7","ErrorMessage":"42703: column SendingEmailProgress.SendStartDate does not exist","Parameters":[]} }
{ "time": "2023-11-23 16:12:00.2307", "level": "WARN", "app": "dotnet", "thread": "63", "message": {"SQL":"\nSELECT\n\t\"BulkEmail\".\"Id\",\n\t\"BulkEmail\".\"CategoryId\",\n\t\"BulkEmail\".\"SendStartDate\",\n\t\"BulkEmail\".\"StatusId\",\n\t\"BulkEmail\".\"LaunchOptionId\"\nFROM\n\t\"public\".\"BulkEmail\"\n\tINNER JOIN \"public\".\"SendingEmailProgress\" ON (\"SendingEmailProgress\".\"BulkEmailId\" = \"BulkEmail\".\"Id\")\n\tLEFT OUTER JOIN \"public\".\"Campaign\" ON (\"Campaign\".\"Id\" = \"BulkEmail\".\"CampaignId\")\nWHERE\n\t\"BulkEmail\".\"StatusId\" IN (@P1, @P2, @P3, @P4, @P5)\n\tAND \"Campaign\".\"CampaignSchemaUId\" IS NULL\n\tAND \"SendingEmailProgress\".\"SendStartDate\" < @P6\n\tAND \"SendingEmailProgress\".\"SendStartDate\" > @P7","ErrorMessage":"42703: column SendingEmailProgress.SendStartDate does not exist","Parameters":[]} }
{ "time": "2023-11-23 16:17:00.2508", "level": "WARN", "app": "dotnet", "thread": "109", "message": {"SQL":"\nSELECT\n\t\"BulkEmail\".\"Id\",\n\t\"BulkEmail\".\"CategoryId\",\n\t\"BulkEmail\".\"SendStartDate\",\n\t\"BulkEmail\".\"StatusId\",\n\t\"BulkEmail\".\"LaunchOptionId\"\nFROM\n\t\"public\".\"BulkEmail\"\n\tINNER JOIN \"public\".\"SendingEmailProgress\" ON (\"SendingEmailProgress\".\"BulkEmailId\" = \"BulkEmail\".\"Id\")\n\tLEFT OUTER JOIN \"public\".\"Campaign\" ON (\"Campaign\".\"Id\" = \"BulkEmail\".\"CampaignId\")\nWHERE\n\t\"BulkEmail\".\"StatusId\" IN (@P1, @P2, @P3, @P4, @P5)\n\tAND \"Campaign\".\"CampaignSchemaUId\" IS NULL\n\tAND \"SendingEmailProgress\".\"SendStartDate\" < @P6\n\tAND \"SendingEmailProgress\".\"SendStartDate\" > @P7","ErrorMessage":"42703: column SendingEmailProgress.SendStartDate does not exist","Parameters":[]} }
{ "time": "2023-11-23 16:22:00.2551", "level": "WARN", "app": "dotnet", "thread": "80", "message": {"SQL":"\nSELECT\n\t\"BulkEmail\".\"Id\",\n\t\"BulkEmail\".\"CategoryId\",\n\t\"BulkEmail\".\"SendStartDate\",\n\t\"BulkEmail\".\"StatusId\",\n\t\"BulkEmail\".\"LaunchOptionId\"\nFROM\n\t\"public\".\"BulkEmail\"\n\tINNER JOIN \"public\".\"SendingEmailProgress\" ON (\"SendingEmailProgress\".\"BulkEmailId\" = \"BulkEmail\".\"Id\")\n\tLEFT OUTER JOIN \"public\".\"Campaign\" ON (\"Campaign\".\"Id\" = \"BulkEmail\".\"CampaignId\")\nWHERE\n\t\"BulkEmail\".\"StatusId\" IN (@P1, @P2, @P3, @P4, @P5)\n\tAND \"Campaign\".\"CampaignSchemaUId\" IS NULL\n\tAND \"SendingEmailProgress\".\"SendStartDate\" < @P6\n\tAND \"SendingEmailProgress\".\"SendStartDate\" > @P7","ErrorMessage":"42703: column SendingEmailProgress.SendStartDate does not exist","Parameters":[]} }
{ "time": "2023-11-23 16:27:00.2578", "level": "WARN", "app": "dotnet", "thread": "17", "message": {"SQL":"\nSELECT\n\t\"BulkEmail\".\"Id\",\n\t\"BulkEmail\".\"CategoryId\",\n\t\"BulkEmail\".\"SendStartDate\",\n\t\"BulkEmail\".\"StatusId\",\n\t\"BulkEmail\".\"LaunchOptionId\"\nFROM\n\t\"public\".\"BulkEmail\"\n\tINNER JOIN \"public\".\"SendingEmailProgress\" ON (\"SendingEmailProgress\".\"BulkEmailId\" = \"BulkEmail\".\"Id\")\n\tLEFT OUTER JOIN \"public\".\"Campaign\" ON (\"Campaign\".\"Id\" = \"BulkEmail\".\"CampaignId\")\nWHERE\n\t\"BulkEmail\".\"StatusId\" IN (@P1, @P2, @P3, @P4, @P5)\n\tAND \"Campaign\".\"CampaignSchemaUId\" IS NULL\n\tAND \"SendingEmailProgress\".\"SendStartDate\" < @P6\n\tAND \"SendingEmailProgress\".\"SendStartDate\" > @P7","ErrorMessage":"42703: column SendingEmailProgress.SendStartDate does not exist","Parameters":[]} }
{ "time": "2023-11-23 16:32:00.2506", "level": "WARN", "app": "dotnet", "thread": "98", "message": {"SQL":"\nSELECT\n\t\"BulkEmail\".\"Id\",\n\t\"BulkEmail\".\"CategoryId\",\n\t\"BulkEmail\".\"SendStartDate\",\n\t\"BulkEmail\".\"StatusId\",\n\t\"BulkEmail\".\"LaunchOptionId\"\nFROM\n\t\"public\".\"BulkEmail\"\n\tINNER JOIN \"public\".\"SendingEmailProgress\" ON (\"SendingEmailProgress\".\"BulkEmailId\" = \"BulkEmail\".\"Id\")\n\tLEFT OUTER JOIN \"public\".\"Campaign\" ON (\"Campaign\".\"Id\" = \"BulkEmail\".\"CampaignId\")\nWHERE\n\t\"BulkEmail\".\"StatusId\" IN (@P1, @P2, @P3, @P4, @P5)\n\tAND \"Campaign\".\"CampaignSchemaUId\" IS NULL\n\tAND \"SendingEmailProgress\".\"SendStartDate\" < @P6\n\tAND \"SendingEmailProgress\".\"SendStartDate\" > @P7","ErrorMessage":"42703: column SendingEmailProgress.SendStartDate does not exist","Parameters":[]} }
{ "time": "2023-11-23 16:37:00.2280", "level": "WARN", "app": "dotnet", "thread": "110", "message": {"SQL":"\nSELECT\n\t\"BulkEmail\".\"Id\",\n\t\"BulkEmail\".\"CategoryId\",\n\t\"BulkEmail\".\"SendStartDate\",\n\t\"BulkEmail\".\"StatusId\",\n\t\"BulkEmail\".\"LaunchOptionId\"\nFROM\n\t\"public\".\"BulkEmail\"\n\tINNER JOIN \"public\".\"SendingEmailProgress\" ON (\"SendingEmailProgress\".\"BulkEmailId\" = \"BulkEmail\".\"Id\")\n\tLEFT OUTER JOIN \"public\".\"Campaign\" ON (\"Campaign\".\"Id\" = \"BulkEmail\".\"CampaignId\")\nWHERE\n\t\"BulkEmail\".\"StatusId\" IN (@P1, @P2, @P3, @P4, @P5)\n\tAND \"Campaign\".\"CampaignSchemaUId\" IS NULL\n\tAND \"SendingEmailProgress\".\"SendStartDate\" < @P6\n\tAND \"SendingEmailProgress\".\"SendStartDate\" > @P7","ErrorMessage":"42703: column SendingEmailProgress.SendStartDate does not exist","Parameters":[]} }
{ "time": "2023-11-23 16:42:00.2337", "level": "WARN", "app": "dotnet", "thread": "60", "message": {"SQL":"\nSELECT\n\t\"BulkEmail\".\"Id\",\n\t\"BulkEmail\".\"CategoryId\",\n\t\"BulkEmail\".\"SendStartDate\",\n\t\"BulkEmail\".\"StatusId\",\n\t\"BulkEmail\".\"LaunchOptionId\"\nFROM\n\t\"public\".\"BulkEmail\"\n\tINNER JOIN \"public\".\"SendingEmailProgress\" ON (\"SendingEmailProgress\".\"BulkEmailId\" = \"BulkEmail\".\"Id\")\n\tLEFT OUTER JOIN \"public\".\"Campaign\" ON (\"Campaign\".\"Id\" = \"BulkEmail\".\"CampaignId\")\nWHERE\n\t\"BulkEmail\".\"StatusId\" IN (@P1, @P2, @P3, @P4, @P5)\n\tAND \"Campaign\".\"CampaignSchemaUId\" IS NULL\n\tAND \"SendingEmailProgress\".\"SendStartDate\" < @P6\n\tAND \"SendingEmailProgress\".\"SendStartDate\" > @P7","ErrorMessage":"42703: column SendingEmailProgress.SendStartDate does not exist","Parameters":[]} }
{ "time": "2023-11-23 16:47:00.2387", "level": "WARN", "app": "dotnet", "thread": "90", "message": {"SQL":"\nSELECT\n\t\"BulkEmail\".\"Id\",\n\t\"BulkEmail\".\"CategoryId\",\n\t\"BulkEmail\".\"SendStartDate\",\n\t\"BulkEmail\".\"StatusId\",\n\t\"BulkEmail\".\"LaunchOptionId\"\nFROM\n\t\"public\".\"BulkEmail\"\n\tINNER JOIN \"public\".\"SendingEmailProgress\" ON (\"SendingEmailProgress\".\"BulkEmailId\" = \"BulkEmail\".\"Id\")\n\tLEFT OUTER JOIN \"public\".\"Campaign\" ON (\"Campaign\".\"Id\" = \"BulkEmail\".\"CampaignId\")\nWHERE\n\t\"BulkEmail\".\"StatusId\" IN (@P1, @P2, @P3, @P4, @P5)\n\tAND \"Campaign\".\"CampaignSchemaUId\" IS NULL\n\tAND \"SendingEmailProgress\".\"SendStartDate\" < @P6\n\tAND \"SendingEmailProgress\".\"SendStartDate\" > @P7","ErrorMessage":"42703: column SendingEmailProgress.SendStartDate does not exist","Parameters":[]} }
{ "time": "2023-11-23 16:52:00.2473", "level": "WARN", "app": "dotnet", "thread": "100", "message": {"SQL":"\nSELECT\n\t\"BulkEmail\".\"Id\",\n\t\"BulkEmail\".\"CategoryId\",\n\t\"BulkEmail\".\"SendStartDate\",\n\t\"BulkEmail\".\"StatusId\",\n\t\"BulkEmail\".\"LaunchOptionId\"\nFROM\n\t\"public\".\"BulkEmail\"\n\tINNER JOIN \"public\".\"SendingEmailProgress\" ON (\"SendingEmailProgress\".\"BulkEmailId\" = \"BulkEmail\".\"Id\")\n\tLEFT OUTER JOIN \"public\".\"Campaign\" ON (\"Campaign\".\"Id\" = \"BulkEmail\".\"CampaignId\")\nWHERE\n\t\"BulkEmail\".\"StatusId\" IN (@P1, @P2, @P3, @P4, @P5)\n\tAND \"Campaign\".\"CampaignSchemaUId\" IS NULL\n\tAND \"SendingEmailProgress\".\"SendStartDate\" < @P6\n\tAND \"SendingEmailProgress\".\"SendStartDate\" > @P7","ErrorMessage":"42703: column SendingEmailProgress.SendStartDate does not exist","Parameters":[]} }
{ "time": "2023-11-23 16:57:00.2675", "level": "WARN", "app": "dotnet", "thread": "85", "message": {"SQL":"\nSELECT\n\t\"BulkEmail\".\"Id\",\n\t\"BulkEmail\".\"CategoryId\",\n\t\"BulkEmail\".\"SendStartDate\",\n\t\"BulkEmail\".\"StatusId\",\n\t\"BulkEmail\".\"LaunchOptionId\"\nFROM\n\t\"public\".\"BulkEmail\"\n\tINNER JOIN \"public\".\"SendingEmailProgress\" ON (\"SendingEmailProgress\".\"BulkEmailId\" = \"BulkEmail\".\"Id\")\n\tLEFT OUTER JOIN \"public\".\"Campaign\" ON (\"Campaign\".\"Id\" = \"BulkEmail\".\"CampaignId\")\nWHERE\n\t\"BulkEmail\".\"StatusId\" IN (@P1, @P2, @P3, @P4, @P5)\n\tAND \"Campaign\".\"CampaignSchemaUId\" IS NULL\n\tAND \"SendingEmailProgress\".\"SendStartDate\" < @P6\n\tAND \"SendingEmailProgress\".\"SendStartDate\" > @P7","ErrorMessage":"42703: column SendingEmailProgress.SendStartDate does not exist","Parameters":[]} }
{ "time": "2023-11-23 17:02:00.2301", "level": "WARN", "app": "dotnet", "thread": "111", "message": {"SQL":"\nSELECT\n\t\"BulkEmail\".\"Id\",\n\t\"BulkEmail\".\"CategoryId\",\n\t\"BulkEmail\".\"SendStartDate\",\n\t\"BulkEmail\".\"StatusId\",\n\t\"BulkEmail\".\"LaunchOptionId\"\nFROM\n\t\"public\".\"BulkEmail\"\n\tINNER JOIN \"public\".\"SendingEmailProgress\" ON (\"SendingEmailProgress\".\"BulkEmailId\" = \"BulkEmail\".\"Id\")\n\tLEFT OUTER JOIN \"public\".\"Campaign\" ON (\"Campaign\".\"Id\" = \"BulkEmail\".\"CampaignId\")\nWHERE\n\t\"BulkEmail\".\"StatusId\" IN (@P1, @P2, @P3, @P4, @P5)\n\tAND \"Campaign\".\"CampaignSchemaUId\" IS NULL\n\tAND \"SendingEmailProgress\".\"SendStartDate\" < @P6\n\tAND \"SendingEmailProgress\".\"SendStartDate\" > @P7","ErrorMessage":"42703: column SendingEmailProgress.SendStartDate does not exist","Parameters":[]} }
{ "time": "2023-11-23 17:07:00.2502", "level": "WARN", "app": "dotnet", "thread": "12", "message": {"SQL":"\nSELECT\n\t\"BulkEmail\".\"Id\",\n\t\"BulkEmail\".\"CategoryId\",\n\t\"BulkEmail\".\"SendStartDate\",\n\t\"BulkEmail\".\"StatusId\",\n\t\"BulkEmail\".\"LaunchOptionId\"\nFROM\n\t\"public\".\"BulkEmail\"\n\tINNER JOIN \"public\".\"SendingEmailProgress\" ON (\"SendingEmailProgress\".\"BulkEmailId\" = \"BulkEmail\".\"Id\")\n\tLEFT OUTER JOIN \"public\".\"Campaign\" ON (\"Campaign\".\"Id\" = \"BulkEmail\".\"CampaignId\")\nWHERE\n\t\"BulkEmail\".\"StatusId\" IN (@P1, @P2, @P3, @P4, @P5)\n\tAND \"Campaign\".\"CampaignSchemaUId\" IS NULL\n\tAND \"SendingEmailProgress\".\"SendStartDate\" < @P6\n\tAND \"SendingEmailProgress\".\"SendStartDate\" > @P7","ErrorMessage":"42703: column SendingEmailProgress.SendStartDate does not exist","Parameters":[]} }
{ "time": "2023-11-23 17:12:00.2548", "level": "WARN", "app": "dotnet", "thread": "112", "message": {"SQL":"\nSELECT\n\t\"BulkEmail\".\"Id\",\n\t\"BulkEmail\".\"CategoryId\",\n\t\"BulkEmail\".\"SendStartDate\",\n\t\"BulkEmail\".\"StatusId\",\n\t\"BulkEmail\".\"LaunchOptionId\"\nFROM\n\t\"public\".\"BulkEmail\"\n\tINNER JOIN \"public\".\"SendingEmailProgress\" ON (\"SendingEmailProgress\".\"BulkEmailId\" = \"BulkEmail\".\"Id\")\n\tLEFT OUTER JOIN \"public\".\"Campaign\" ON (\"Campaign\".\"Id\" = \"BulkEmail\".\"CampaignId\")\nWHERE\n\t\"BulkEmail\".\"StatusId\" IN (@P1, @P2, @P3, @P4, @P5)\n\tAND \"Campaign\".\"CampaignSchemaUId\" IS NULL\n\tAND \"SendingEmailProgress\".\"SendStartDate\" < @P6\n\tAND \"SendingEmailProgress\".\"SendStartDate\" > @P7","ErrorMessage":"42703: column SendingEmailProgress.SendStartDate does not exist","Parameters":[]} }
{ "time": "2023-11-23 17:17:00.2509", "level": "WARN", "app": "dotnet", "thread": "64", "message": {"SQL":"\nSELECT\n\t\"BulkEmail\".\"Id\",\n\t\"BulkEmail\".\"CategoryId\",\n\t\"BulkEmail\".\"SendStartDate\",\n\t\"BulkEmail\".\"StatusId\",\n\t\"BulkEmail\".\"LaunchOptionId\"\nFROM\n\t\"public\".\"BulkEmail\"\n\tINNER JOIN \"public\".\"SendingEmailProgress\" ON (\"SendingEmailProgress\".\"BulkEmailId\" = \"BulkEmail\".\"Id\")\n\tLEFT OUTER JOIN \"public\".\"Campaign\" ON (\"Campaign\".\"Id\" = \"BulkEmail\".\"CampaignId\")\nWHERE\n\t\"BulkEmail\".\"StatusId\" IN (@P1, @P2, @P3, @P4, @P5)\n\tAND \"Campaign\".\"CampaignSchemaUId\" IS NULL\n\tAND \"SendingEmailProgress\".\"SendStartDate\" < @P6\n\tAND \"SendingEmailProgress\".\"SendStartDate\" > @P7","ErrorMessage":"42703: column SendingEmailProgress.SendStartDate does not exist","Parameters":[]} }
{ "time": "2023-11-23 17:22:00.2423", "level": "WARN", "app": "dotnet", "thread": "129", "message": {"SQL":"\nSELECT\n\t\"BulkEmail\".\"Id\",\n\t\"BulkEmail\".\"CategoryId\",\n\t\"BulkEmail\".\"SendStartDate\",\n\t\"BulkEmail\".\"StatusId\",\n\t\"BulkEmail\".\"LaunchOptionId\"\nFROM\n\t\"public\".\"BulkEmail\"\n\tINNER JOIN \"public\".\"SendingEmailProgress\" ON (\"SendingEmailProgress\".\"BulkEmailId\" = \"BulkEmail\".\"Id\")\n\tLEFT OUTER JOIN \"public\".\"Campaign\" ON (\"Campaign\".\"Id\" = \"BulkEmail\".\"CampaignId\")\nWHERE\n\t\"BulkEmail\".\"StatusId\" IN (@P1, @P2, @P3, @P4, @P5)\n\tAND \"Campaign\".\"CampaignSchemaUId\" IS NULL\n\tAND \"SendingEmailProgress\".\"SendStartDate\" < @P6\n\tAND \"SendingEmailProgress\".\"SendStartDate\" > @P7","ErrorMessage":"42703: column SendingEmailProgress.SendStartDate does not exist","Parameters":[]} }
{ "time": "2023-11-23 17:27:00.2455", "level": "WARN", "app": "dotnet", "thread": "18", "message": {"SQL":"\nSELECT\n\t\"BulkEmail\".\"Id\",\n\t\"BulkEmail\".\"CategoryId\",\n\t\"BulkEmail\".\"SendStartDate\",\n\t\"BulkEmail\".\"StatusId\",\n\t\"BulkEmail\".\"LaunchOptionId\"\nFROM\n\t\"public\".\"BulkEmail\"\n\tINNER JOIN \"public\".\"SendingEmailProgress\" ON (\"SendingEmailProgress\".\"BulkEmailId\" = \"BulkEmail\".\"Id\")\n\tLEFT OUTER JOIN \"public\".\"Campaign\" ON (\"Campaign\".\"Id\" = \"BulkEmail\".\"CampaignId\")\nWHERE\n\t\"BulkEmail\".\"StatusId\" IN (@P1, @P2, @P3, @P4, @P5)\n\tAND \"Campaign\".\"CampaignSchemaUId\" IS NULL\n\tAND \"SendingEmailProgress\".\"SendStartDate\" < @P6\n\tAND \"SendingEmailProgress\".\"SendStartDate\" > @P7","ErrorMessage":"42703: column SendingEmailProgress.SendStartDate does not exist","Parameters":[]} }
{ "time": "2023-11-23 17:32:00.2587", "level": "WARN", "app": "dotnet", "thread": "84", "message": {"SQL":"\nSELECT\n\t\"BulkEmail\".\"Id\",\n\t\"BulkEmail\".\"CategoryId\",\n\t\"BulkEmail\".\"SendStartDate\",\n\t\"BulkEmail\".\"StatusId\",\n\t\"BulkEmail\".\"LaunchOptionId\"\nFROM\n\t\"public\".\"BulkEmail\"\n\tINNER JOIN \"public\".\"SendingEmailProgress\" ON (\"SendingEmailProgress\".\"BulkEmailId\" = \"BulkEmail\".\"Id\")\n\tLEFT OUTER JOIN \"public\".\"Campaign\" ON (\"Campaign\".\"Id\" = \"BulkEmail\".\"CampaignId\")\nWHERE\n\t\"BulkEmail\".\"StatusId\" IN (@P1, @P2, @P3, @P4, @P5)\n\tAND \"Campaign\".\"CampaignSchemaUId\" IS NULL\n\tAND \"SendingEmailProgress\".\"SendStartDate\" < @P6\n\tAND \"SendingEmailProgress\".\"SendStartDate\" > @P7","ErrorMessage":"42703: column SendingEmailProgress.SendStartDate does not exist","Parameters":[]} }
{ "time": "2023-11-23 17:37:00.2458", "level": "WARN", "app": "dotnet", "thread": "64", "message": {"SQL":"\nSELECT\n\t\"BulkEmail\".\"Id\",\n\t\"BulkEmail\".\"CategoryId\",\n\t\"BulkEmail\".\"SendStartDate\",\n\t\"BulkEmail\".\"StatusId\",\n\t\"BulkEmail\".\"LaunchOptionId\"\nFROM\n\t\"public\".\"BulkEmail\"\n\tINNER JOIN \"public\".\"SendingEmailProgress\" ON (\"SendingEmailProgress\".\"BulkEmailId\" = \"BulkEmail\".\"Id\")\n\tLEFT OUTER JOIN \"public\".\"Campaign\" ON (\"Campaign\".\"Id\" = \"BulkEmail\".\"CampaignId\")\nWHERE\n\t\"BulkEmail\".\"StatusId\" IN (@P1, @P2, @P3, @P4, @P5)\n\tAND \"Campaign\".\"CampaignSchemaUId\" IS NULL\n\tAND \"SendingEmailProgress\".\"SendStartDate\" < @P6\n\tAND \"SendingEmailProgress\".\"SendStartDate\" > @P7","ErrorMessage":"42703: column SendingEmailProgress.SendStartDate does not exist","Parameters":[]} }
{ "time": "2023-11-23 17:42:00.2429", "level": "WARN", "app": "dotnet", "thread": "100", "message": {"SQL":"\nSELECT\n\t\"BulkEmail\".\"Id\",\n\t\"BulkEmail\".\"CategoryId\",\n\t\"BulkEmail\".\"SendStartDate\",\n\t\"BulkEmail\".\"StatusId\",\n\t\"BulkEmail\".\"LaunchOptionId\"\nFROM\n\t\"public\".\"BulkEmail\"\n\tINNER JOIN \"public\".\"SendingEmailProgress\" ON (\"SendingEmailProgress\".\"BulkEmailId\" = \"BulkEmail\".\"Id\")\n\tLEFT OUTER JOIN \"public\".\"Campaign\" ON (\"Campaign\".\"Id\" = \"BulkEmail\".\"CampaignId\")\nWHERE\n\t\"BulkEmail\".\"StatusId\" IN (@P1, @P2, @P3, @P4, @P5)\n\tAND \"Campaign\".\"CampaignSchemaUId\" IS NULL\n\tAND \"SendingEmailProgress\".\"SendStartDate\" < @P6\n\tAND \"SendingEmailProgress\".\"SendStartDate\" > @P7","ErrorMessage":"42703: column SendingEmailProgress.SendStartDate does not exist","Parameters":[]} }
{ "time": "2023-11-23 17:47:00.2507", "level": "WARN", "app": "dotnet", "thread": "48", "message": {"SQL":"\nSELECT\n\t\"BulkEmail\".\"Id\",\n\t\"BulkEmail\".\"CategoryId\",\n\t\"BulkEmail\".\"SendStartDate\",\n\t\"BulkEmail\".\"StatusId\",\n\t\"BulkEmail\".\"LaunchOptionId\"\nFROM\n\t\"public\".\"BulkEmail\"\n\tINNER JOIN \"public\".\"SendingEmailProgress\" ON (\"SendingEmailProgress\".\"BulkEmailId\" = \"BulkEmail\".\"Id\")\n\tLEFT OUTER JOIN \"public\".\"Campaign\" ON (\"Campaign\".\"Id\" = \"BulkEmail\".\"CampaignId\")\nWHERE\n\t\"BulkEmail\".\"StatusId\" IN (@P1, @P2, @P3, @P4, @P5)\n\tAND \"Campaign\".\"CampaignSchemaUId\" IS NULL\n\tAND \"SendingEmailProgress\".\"SendStartDate\" < @P6\n\tAND \"SendingEmailProgress\".\"SendStartDate\" > @P7","ErrorMessage":"42703: column SendingEmailProgress.SendStartDate does not exist","Parameters":[]} }
{ "time": "2023-11-23 17:52:00.2504", "level": "WARN", "app": "dotnet", "thread": "118", "message": {"SQL":"\nSELECT\n\t\"BulkEmail\".\"Id\",\n\t\"BulkEmail\".\"CategoryId\",\n\t\"BulkEmail\".\"SendStartDate\",\n\t\"BulkEmail\".\"StatusId\",\n\t\"BulkEmail\".\"LaunchOptionId\"\nFROM\n\t\"public\".\"BulkEmail\"\n\tINNER JOIN \"public\".\"SendingEmailProgress\" ON (\"SendingEmailProgress\".\"BulkEmailId\" = \"BulkEmail\".\"Id\")\n\tLEFT OUTER JOIN \"public\".\"Campaign\" ON (\"Campaign\".\"Id\" = \"BulkEmail\".\"CampaignId\")\nWHERE\n\t\"BulkEmail\".\"StatusId\" IN (@P1, @P2, @P3, @P4, @P5)\n\tAND \"Campaign\".\"CampaignSchemaUId\" IS NULL\n\tAND \"SendingEmailProgress\".\"SendStartDate\" < @P6\n\tAND \"SendingEmailProgress\".\"SendStartDate\" > @P7","ErrorMessage":"42703: column SendingEmailProgress.SendStartDate does not exist","Parameters":[]} }
{ "time": "2023-11-23 17:57:00.2436", "level": "WARN", "app": "dotnet", "thread": "98", "message": {"SQL":"\nSELECT\n\t\"BulkEmail\".\"Id\",\n\t\"BulkEmail\".\"CategoryId\",\n\t\"BulkEmail\".\"SendStartDate\",\n\t\"BulkEmail\".\"StatusId\",\n\t\"BulkEmail\".\"LaunchOptionId\"\nFROM\n\t\"public\".\"BulkEmail\"\n\tINNER JOIN \"public\".\"SendingEmailProgress\" ON (\"SendingEmailProgress\".\"BulkEmailId\" = \"BulkEmail\".\"Id\")\n\tLEFT OUTER JOIN \"public\".\"Campaign\" ON (\"Campaign\".\"Id\" = \"BulkEmail\".\"CampaignId\")\nWHERE\n\t\"BulkEmail\".\"StatusId\" IN (@P1, @P2, @P3, @P4, @P5)\n\tAND \"Campaign\".\"CampaignSchemaUId\" IS NULL\n\tAND \"SendingEmailProgress\".\"SendStartDate\" < @P6\n\tAND \"SendingEmailProgress\".\"SendStartDate\" > @P7","ErrorMessage":"42703: column SendingEmailProgress.SendStartDate does not exist","Parameters":[]} }
{ "time": "2023-11-23 18:02:00.2905", "level": "WARN", "app": "dotnet", "thread": "113", "message": {"SQL":"\nSELECT\n\t\"BulkEmail\".\"Id\",\n\t\"BulkEmail\".\"CategoryId\",\n\t\"BulkEmail\".\"SendStartDate\",\n\t\"BulkEmail\".\"StatusId\",\n\t\"BulkEmail\".\"LaunchOptionId\"\nFROM\n\t\"public\".\"BulkEmail\"\n\tINNER JOIN \"public\".\"SendingEmailProgress\" ON (\"SendingEmailProgress\".\"BulkEmailId\" = \"BulkEmail\".\"Id\")\n\tLEFT OUTER JOIN \"public\".\"Campaign\" ON (\"Campaign\".\"Id\" = \"BulkEmail\".\"CampaignId\")\nWHERE\n\t\"BulkEmail\".\"StatusId\" IN (@P1, @P2, @P3, @P4, @P5)\n\tAND \"Campaign\".\"CampaignSchemaUId\" IS NULL\n\tAND \"SendingEmailProgress\".\"SendStartDate\" < @P6\n\tAND \"SendingEmailProgress\".\"SendStartDate\" > @P7","ErrorMessage":"42703: column SendingEmailProgress.SendStartDate does not exist","Parameters":[]} }
{ "time": "2023-11-23 18:07:00.2729", "level": "WARN", "app": "dotnet", "thread": "139", "message": {"SQL":"\nSELECT\n\t\"BulkEmail\".\"Id\",\n\t\"BulkEmail\".\"CategoryId\",\n\t\"BulkEmail\".\"SendStartDate\",\n\t\"BulkEmail\".\"StatusId\",\n\t\"BulkEmail\".\"LaunchOptionId\"\nFROM\n\t\"public\".\"BulkEmail\"\n\tINNER JOIN \"public\".\"SendingEmailProgress\" ON (\"SendingEmailProgress\".\"BulkEmailId\" = \"BulkEmail\".\"Id\")\n\tLEFT OUTER JOIN \"public\".\"Campaign\" ON (\"Campaign\".\"Id\" = \"BulkEmail\".\"CampaignId\")\nWHERE\n\t\"BulkEmail\".\"StatusId\" IN (@P1, @P2, @P3, @P4, @P5)\n\tAND \"Campaign\".\"CampaignSchemaUId\" IS NULL\n\tAND \"SendingEmailProgress\".\"SendStartDate\" < @P6\n\tAND \"SendingEmailProgress\".\"SendStartDate\" > @P7","ErrorMessage":"42703: column SendingEmailProgress.SendStartDate does not exist","Parameters":[]} }
{ "time": "2023-11-23 18:12:00.2556", "level": "WARN", "app": "dotnet", "thread": "131", "message": {"SQL":"\nSELECT\n\t\"BulkEmail\".\"Id\",\n\t\"BulkEmail\".\"CategoryId\",\n\t\"BulkEmail\".\"SendStartDate\",\n\t\"BulkEmail\".\"StatusId\",\n\t\"BulkEmail\".\"LaunchOptionId\"\nFROM\n\t\"public\".\"BulkEmail\"\n\tINNER JOIN \"public\".\"SendingEmailProgress\" ON (\"SendingEmailProgress\".\"BulkEmailId\" = \"BulkEmail\".\"Id\")\n\tLEFT OUTER JOIN \"public\".\"Campaign\" ON (\"Campaign\".\"Id\" = \"BulkEmail\".\"CampaignId\")\nWHERE\n\t\"BulkEmail\".\"StatusId\" IN (@P1, @P2, @P3, @P4, @P5)\n\tAND \"Campaign\".\"CampaignSchemaUId\" IS NULL\n\tAND \"SendingEmailProgress\".\"SendStartDate\" < @P6\n\tAND \"SendingEmailProgress\".\"SendStartDate\" > @P7","ErrorMessage":"42703: column SendingEmailProgress.SendStartDate does not exist","Parameters":[]} }
{ "time": "2023-11-23 18:17:00.2473", "level": "WARN", "app": "dotnet", "thread": "79", "message": {"SQL":"\nSELECT\n\t\"BulkEmail\".\"Id\",\n\t\"BulkEmail\".\"CategoryId\",\n\t\"BulkEmail\".\"SendStartDate\",\n\t\"BulkEmail\".\"StatusId\",\n\t\"BulkEmail\".\"LaunchOptionId\"\nFROM\n\t\"public\".\"BulkEmail\"\n\tINNER JOIN \"public\".\"SendingEmailProgress\" ON (\"SendingEmailProgress\".\"BulkEmailId\" = \"BulkEmail\".\"Id\")\n\tLEFT OUTER JOIN \"public\".\"Campaign\" ON (\"Campaign\".\"Id\" = \"BulkEmail\".\"CampaignId\")\nWHERE\n\t\"BulkEmail\".\"StatusId\" IN (@P1, @P2, @P3, @P4, @P5)\n\tAND \"Campaign\".\"CampaignSchemaUId\" IS NULL\n\tAND \"SendingEmailProgress\".\"SendStartDate\" < @P6\n\tAND \"SendingEmailProgress\".\"SendStartDate\" > @P7","ErrorMessage":"42703: column SendingEmailProgress.SendStartDate does not exist","Parameters":[]} }
{ "time": "2023-11-23 18:22:00.2503", "level": "WARN", "app": "dotnet", "thread": "62", "message": {"SQL":"\nSELECT\n\t\"BulkEmail\".\"Id\",\n\t\"BulkEmail\".\"CategoryId\",\n\t\"BulkEmail\".\"SendStartDate\",\n\t\"BulkEmail\".\"StatusId\",\n\t\"BulkEmail\".\"LaunchOptionId\"\nFROM\n\t\"public\".\"BulkEmail\"\n\tINNER JOIN \"public\".\"SendingEmailProgress\" ON (\"SendingEmailProgress\".\"BulkEmailId\" = \"BulkEmail\".\"Id\")\n\tLEFT OUTER JOIN \"public\".\"Campaign\" ON (\"Campaign\".\"Id\" = \"BulkEmail\".\"CampaignId\")\nWHERE\n\t\"BulkEmail\".\"StatusId\" IN (@P1, @P2, @P3, @P4, @P5)\n\tAND \"Campaign\".\"CampaignSchemaUId\" IS NULL\n\tAND \"SendingEmailProgress\".\"SendStartDate\" < @P6\n\tAND \"SendingEmailProgress\".\"SendStartDate\" > @P7","ErrorMessage":"42703: column SendingEmailProgress.SendStartDate does not exist","Parameters":[]} }
{ "time": "2023-11-23 18:27:00.2468", "level": "WARN", "app": "dotnet", "thread": "97", "message": {"SQL":"\nSELECT\n\t\"BulkEmail\".\"Id\",\n\t\"BulkEmail\".\"CategoryId\",\n\t\"BulkEmail\".\"SendStartDate\",\n\t\"BulkEmail\".\"StatusId\",\n\t\"BulkEmail\".\"LaunchOptionId\"\nFROM\n\t\"public\".\"BulkEmail\"\n\tINNER JOIN \"public\".\"SendingEmailProgress\" ON (\"SendingEmailProgress\".\"BulkEmailId\" = \"BulkEmail\".\"Id\")\n\tLEFT OUTER JOIN \"public\".\"Campaign\" ON (\"Campaign\".\"Id\" = \"BulkEmail\".\"CampaignId\")\nWHERE\n\t\"BulkEmail\".\"StatusId\" IN (@P1, @P2, @P3, @P4, @P5)\n\tAND \"Campaign\".\"CampaignSchemaUId\" IS NULL\n\tAND \"SendingEmailProgress\".\"SendStartDate\" < @P6\n\tAND \"SendingEmailProgress\".\"SendStartDate\" > @P7","ErrorMessage":"42703: column SendingEmailProgress.SendStartDate does not exist","Parameters":[]} }
{ "time": "2023-11-23 18:32:00.2683", "level": "WARN", "app": "dotnet", "thread": "12", "message": {"SQL":"\nSELECT\n\t\"BulkEmail\".\"Id\",\n\t\"BulkEmail\".\"CategoryId\",\n\t\"BulkEmail\".\"SendStartDate\",\n\t\"BulkEmail\".\"StatusId\",\n\t\"BulkEmail\".\"LaunchOptionId\"\nFROM\n\t\"public\".\"BulkEmail\"\n\tINNER JOIN \"public\".\"SendingEmailProgress\" ON (\"SendingEmailProgress\".\"BulkEmailId\" = \"BulkEmail\".\"Id\")\n\tLEFT OUTER JOIN \"public\".\"Campaign\" ON (\"Campaign\".\"Id\" = \"BulkEmail\".\"CampaignId\")\nWHERE\n\t\"BulkEmail\".\"StatusId\" IN (@P1, @P2, @P3, @P4, @P5)\n\tAND \"Campaign\".\"CampaignSchemaUId\" IS NULL\n\tAND \"SendingEmailProgress\".\"SendStartDate\" < @P6\n\tAND \"SendingEmailProgress\".\"SendStartDate\" > @P7","ErrorMessage":"42703: column SendingEmailProgress.SendStartDate does not exist","Parameters":[]} }
{ "time": "2023-11-23 18:37:00.2515", "level": "WARN", "app": "dotnet", "thread": "136", "message": {"SQL":"\nSELECT\n\t\"BulkEmail\".\"Id\",\n\t\"BulkEmail\".\"CategoryId\",\n\t\"BulkEmail\".\"SendStartDate\",\n\t\"BulkEmail\".\"StatusId\",\n\t\"BulkEmail\".\"LaunchOptionId\"\nFROM\n\t\"public\".\"BulkEmail\"\n\tINNER JOIN \"public\".\"SendingEmailProgress\" ON (\"SendingEmailProgress\".\"BulkEmailId\" = \"BulkEmail\".\"Id\")\n\tLEFT OUTER JOIN \"public\".\"Campaign\" ON (\"Campaign\".\"Id\" = \"BulkEmail\".\"CampaignId\")\nWHERE\n\t\"BulkEmail\".\"StatusId\" IN (@P1, @P2, @P3, @P4, @P5)\n\tAND \"Campaign\".\"CampaignSchemaUId\" IS NULL\n\tAND \"SendingEmailProgress\".\"SendStartDate\" < @P6\n\tAND \"SendingEmailProgress\".\"SendStartDate\" > @P7","ErrorMessage":"42703: column SendingEmailProgress.SendStartDate does not exist","Parameters":[]} }
{ "time": "2023-11-23 18:42:00.2831", "level": "WARN", "app": "dotnet", "thread": "60", "message": {"SQL":"\nSELECT\n\t\"BulkEmail\".\"Id\",\n\t\"BulkEmail\".\"CategoryId\",\n\t\"BulkEmail\".\"SendStartDate\",\n\t\"BulkEmail\".\"StatusId\",\n\t\"BulkEmail\".\"LaunchOptionId\"\nFROM\n\t\"public\".\"BulkEmail\"\n\tINNER JOIN \"public\".\"SendingEmailProgress\" ON (\"SendingEmailProgress\".\"BulkEmailId\" = \"BulkEmail\".\"Id\")\n\tLEFT OUTER JOIN \"public\".\"Campaign\" ON (\"Campaign\".\"Id\" = \"BulkEmail\".\"CampaignId\")\nWHERE\n\t\"BulkEmail\".\"StatusId\" IN (@P1, @P2, @P3, @P4, @P5)\n\tAND \"Campaign\".\"CampaignSchemaUId\" IS NULL\n\tAND \"SendingEmailProgress\".\"SendStartDate\" < @P6\n\tAND \"SendingEmailProgress\".\"SendStartDate\" > @P7","ErrorMessage":"42703: column SendingEmailProgress.SendStartDate does not exist","Parameters":[]} }
{ "time": "2023-11-23 18:47:00.2548", "level": "WARN", "app": "dotnet", "thread": "89", "message": {"SQL":"\nSELECT\n\t\"BulkEmail\".\"Id\",\n\t\"BulkEmail\".\"CategoryId\",\n\t\"BulkEmail\".\"SendStartDate\",\n\t\"BulkEmail\".\"StatusId\",\n\t\"BulkEmail\".\"LaunchOptionId\"\nFROM\n\t\"public\".\"BulkEmail\"\n\tINNER JOIN \"public\".\"SendingEmailProgress\" ON (\"SendingEmailProgress\".\"BulkEmailId\" = \"BulkEmail\".\"Id\")\n\tLEFT OUTER JOIN \"public\".\"Campaign\" ON (\"Campaign\".\"Id\" = \"BulkEmail\".\"CampaignId\")\nWHERE\n\t\"BulkEmail\".\"StatusId\" IN (@P1, @P2, @P3, @P4, @P5)\n\tAND \"Campaign\".\"CampaignSchemaUId\" IS NULL\n\tAND \"SendingEmailProgress\".\"SendStartDate\" < @P6\n\tAND \"SendingEmailProgress\".\"SendStartDate\" > @P7","ErrorMessage":"42703: column SendingEmailProgress.SendStartDate does not exist","Parameters":[]} }
{ "time": "2023-11-23 18:52:00.2552", "level": "WARN", "app": "dotnet", "thread": "122", "message": {"SQL":"\nSELECT\n\t\"BulkEmail\".\"Id\",\n\t\"BulkEmail\".\"CategoryId\",\n\t\"BulkEmail\".\"SendStartDate\",\n\t\"BulkEmail\".\"StatusId\",\n\t\"BulkEmail\".\"LaunchOptionId\"\nFROM\n\t\"public\".\"BulkEmail\"\n\tINNER JOIN \"public\".\"SendingEmailProgress\" ON (\"SendingEmailProgress\".\"BulkEmailId\" = \"BulkEmail\".\"Id\")\n\tLEFT OUTER JOIN \"public\".\"Campaign\" ON (\"Campaign\".\"Id\" = \"BulkEmail\".\"CampaignId\")\nWHERE\n\t\"BulkEmail\".\"StatusId\" IN (@P1, @P2, @P3, @P4, @P5)\n\tAND \"Campaign\".\"CampaignSchemaUId\" IS NULL\n\tAND \"SendingEmailProgress\".\"SendStartDate\" < @P6\n\tAND \"SendingEmailProgress\".\"SendStartDate\" > @P7","ErrorMessage":"42703: column SendingEmailProgress.SendStartDate does not exist","Parameters":[]} }
{ "time": "2023-11-23 18:57:00.5660", "level": "WARN", "app": "dotnet", "thread": "28", "message": {"SQL":"\nSELECT\n\t\"BulkEmail\".\"Id\",\n\t\"BulkEmail\".\"CategoryId\",\n\t\"BulkEmail\".\"SendStartDate\",\n\t\"BulkEmail\".\"StatusId\",\n\t\"BulkEmail\".\"LaunchOptionId\"\nFROM\n\t\"public\".\"BulkEmail\"\n\tINNER JOIN \"public\".\"SendingEmailProgress\" ON (\"SendingEmailProgress\".\"BulkEmailId\" = \"BulkEmail\".\"Id\")\n\tLEFT OUTER JOIN \"public\".\"Campaign\" ON (\"Campaign\".\"Id\" = \"BulkEmail\".\"CampaignId\")\nWHERE\n\t\"BulkEmail\".\"StatusId\" IN (@P1, @P2, @P3, @P4, @P5)\n\tAND \"Campaign\".\"CampaignSchemaUId\" IS NULL\n\tAND \"SendingEmailProgress\".\"SendStartDate\" < @P6\n\tAND \"SendingEmailProgress\".\"SendStartDate\" > @P7","ErrorMessage":"42703: column SendingEmailProgress.SendStartDate does not exist","Parameters":[]} }
{ "time": "2023-11-23 19:02:00.2300", "level": "WARN", "app": "dotnet", "thread": "94", "message": {"SQL":"\nSELECT\n\t\"BulkEmail\".\"Id\",\n\t\"BulkEmail\".\"CategoryId\",\n\t\"BulkEmail\".\"SendStartDate\",\n\t\"BulkEmail\".\"StatusId\",\n\t\"BulkEmail\".\"LaunchOptionId\"\nFROM\n\t\"public\".\"BulkEmail\"\n\tINNER JOIN \"public\".\"SendingEmailProgress\" ON (\"SendingEmailProgress\".\"BulkEmailId\" = \"BulkEmail\".\"Id\")\n\tLEFT OUTER JOIN \"public\".\"Campaign\" ON (\"Campaign\".\"Id\" = \"BulkEmail\".\"CampaignId\")\nWHERE\n\t\"BulkEmail\".\"StatusId\" IN (@P1, @P2, @P3, @P4, @P5)\n\tAND \"Campaign\".\"CampaignSchemaUId\" IS NULL\n\tAND \"SendingEmailProgress\".\"SendStartDate\" < @P6\n\tAND \"SendingEmailProgress\".\"SendStartDate\" > @P7","ErrorMessage":"42703: column SendingEmailProgress.SendStartDate does not exist","Parameters":[]} }
{ "time": "2023-11-23 19:07:00.2476", "level": "WARN", "app": "dotnet", "thread": "91", "message": {"SQL":"\nSELECT\n\t\"BulkEmail\".\"Id\",\n\t\"BulkEmail\".\"CategoryId\",\n\t\"BulkEmail\".\"SendStartDate\",\n\t\"BulkEmail\".\"StatusId\",\n\t\"BulkEmail\".\"LaunchOptionId\"\nFROM\n\t\"public\".\"BulkEmail\"\n\tINNER JOIN \"public\".\"SendingEmailProgress\" ON (\"SendingEmailProgress\".\"BulkEmailId\" = \"BulkEmail\".\"Id\")\n\tLEFT OUTER JOIN \"public\".\"Campaign\" ON (\"Campaign\".\"Id\" = \"BulkEmail\".\"CampaignId\")\nWHERE\n\t\"BulkEmail\".\"StatusId\" IN (@P1, @P2, @P3, @P4, @P5)\n\tAND \"Campaign\".\"CampaignSchemaUId\" IS NULL\n\tAND \"SendingEmailProgress\".\"SendStartDate\" < @P6\n\tAND \"SendingEmailProgress\".\"SendStartDate\" > @P7","ErrorMessage":"42703: column SendingEmailProgress.SendStartDate does not exist","Parameters":[]} }
{ "time": "2023-11-23 19:12:00.2419", "level": "WARN", "app": "dotnet", "thread": "26", "message": {"SQL":"\nSELECT\n\t\"BulkEmail\".\"Id\",\n\t\"BulkEmail\".\"CategoryId\",\n\t\"BulkEmail\".\"SendStartDate\",\n\t\"BulkEmail\".\"StatusId\",\n\t\"BulkEmail\".\"LaunchOptionId\"\nFROM\n\t\"public\".\"BulkEmail\"\n\tINNER JOIN \"public\".\"SendingEmailProgress\" ON (\"SendingEmailProgress\".\"BulkEmailId\" = \"BulkEmail\".\"Id\")\n\tLEFT OUTER JOIN \"public\".\"Campaign\" ON (\"Campaign\".\"Id\" = \"BulkEmail\".\"CampaignId\")\nWHERE\n\t\"BulkEmail\".\"StatusId\" IN (@P1, @P2, @P3, @P4, @P5)\n\tAND \"Campaign\".\"CampaignSchemaUId\" IS NULL\n\tAND \"SendingEmailProgress\".\"SendStartDate\" < @P6\n\tAND \"SendingEmailProgress\".\"SendStartDate\" > @P7","ErrorMessage":"42703: column SendingEmailProgress.SendStartDate does not exist","Parameters":[]} }
{ "time": "2023-11-23 19:17:00.2336", "level": "WARN", "app": "dotnet", "thread": "53", "message": {"SQL":"\nSELECT\n\t\"BulkEmail\".\"Id\",\n\t\"BulkEmail\".\"CategoryId\",\n\t\"BulkEmail\".\"SendStartDate\",\n\t\"BulkEmail\".\"StatusId\",\n\t\"BulkEmail\".\"LaunchOptionId\"\nFROM\n\t\"public\".\"BulkEmail\"\n\tINNER JOIN \"public\".\"SendingEmailProgress\" ON (\"SendingEmailProgress\".\"BulkEmailId\" = \"BulkEmail\".\"Id\")\n\tLEFT OUTER JOIN \"public\".\"Campaign\" ON (\"Campaign\".\"Id\" = \"BulkEmail\".\"CampaignId\")\nWHERE\n\t\"BulkEmail\".\"StatusId\" IN (@P1, @P2, @P3, @P4, @P5)\n\tAND \"Campaign\".\"CampaignSchemaUId\" IS NULL\n\tAND \"SendingEmailProgress\".\"SendStartDate\" < @P6\n\tAND \"SendingEmailProgress\".\"SendStartDate\" > @P7","ErrorMessage":"42703: column SendingEmailProgress.SendStartDate does not exist","Parameters":[]} }
{ "time": "2023-11-23 19:22:00.2558", "level": "WARN", "app": "dotnet", "thread": "88", "message": {"SQL":"\nSELECT\n\t\"BulkEmail\".\"Id\",\n\t\"BulkEmail\".\"CategoryId\",\n\t\"BulkEmail\".\"SendStartDate\",\n\t\"BulkEmail\".\"StatusId\",\n\t\"BulkEmail\".\"LaunchOptionId\"\nFROM\n\t\"public\".\"BulkEmail\"\n\tINNER JOIN \"public\".\"SendingEmailProgress\" ON (\"SendingEmailProgress\".\"BulkEmailId\" = \"BulkEmail\".\"Id\")\n\tLEFT OUTER JOIN \"public\".\"Campaign\" ON (\"Campaign\".\"Id\" = \"BulkEmail\".\"CampaignId\")\nWHERE\n\t\"BulkEmail\".\"StatusId\" IN (@P1, @P2, @P3, @P4, @P5)\n\tAND \"Campaign\".\"CampaignSchemaUId\" IS NULL\n\tAND \"SendingEmailProgress\".\"SendStartDate\" < @P6\n\tAND \"SendingEmailProgress\".\"SendStartDate\" > @P7","ErrorMessage":"42703: column SendingEmailProgress.SendStartDate does not exist","Parameters":[]} }
{ "time": "2023-11-23 19:27:00.2539", "level": "WARN", "app": "dotnet", "thread": "77", "message": {"SQL":"\nSELECT\n\t\"BulkEmail\".\"Id\",\n\t\"BulkEmail\".\"CategoryId\",\n\t\"BulkEmail\".\"SendStartDate\",\n\t\"BulkEmail\".\"StatusId\",\n\t\"BulkEmail\".\"LaunchOptionId\"\nFROM\n\t\"public\".\"BulkEmail\"\n\tINNER JOIN \"public\".\"SendingEmailProgress\" ON (\"SendingEmailProgress\".\"BulkEmailId\" = \"BulkEmail\".\"Id\")\n\tLEFT OUTER JOIN \"public\".\"Campaign\" ON (\"Campaign\".\"Id\" = \"BulkEmail\".\"CampaignId\")\nWHERE\n\t\"BulkEmail\".\"StatusId\" IN (@P1, @P2, @P3, @P4, @P5)\n\tAND \"Campaign\".\"CampaignSchemaUId\" IS NULL\n\tAND \"SendingEmailProgress\".\"SendStartDate\" < @P6\n\tAND \"SendingEmailProgress\".\"SendStartDate\" > @P7","ErrorMessage":"42703: column SendingEmailProgress.SendStartDate does not exist","Parameters":[]} }
{ "time": "2023-11-23 19:32:00.2339", "level": "WARN", "app": "dotnet", "thread": "98", "message": {"SQL":"\nSELECT\n\t\"BulkEmail\".\"Id\",\n\t\"BulkEmail\".\"CategoryId\",\n\t\"BulkEmail\".\"SendStartDate\",\n\t\"BulkEmail\".\"StatusId\",\n\t\"BulkEmail\".\"LaunchOptionId\"\nFROM\n\t\"public\".\"BulkEmail\"\n\tINNER JOIN \"public\".\"SendingEmailProgress\" ON (\"SendingEmailProgress\".\"BulkEmailId\" = \"BulkEmail\".\"Id\")\n\tLEFT OUTER JOIN \"public\".\"Campaign\" ON (\"Campaign\".\"Id\" = \"BulkEmail\".\"CampaignId\")\nWHERE\n\t\"BulkEmail\".\"StatusId\" IN (@P1, @P2, @P3, @P4, @P5)\n\tAND \"Campaign\".\"CampaignSchemaUId\" IS NULL\n\tAND \"SendingEmailProgress\".\"SendStartDate\" < @P6\n\tAND \"SendingEmailProgress\".\"SendStartDate\" > @P7","ErrorMessage":"42703: column SendingEmailProgress.SendStartDate does not exist","Parameters":[]} }
{ "time": "2023-11-23 19:37:00.2503", "level": "WARN", "app": "dotnet", "thread": "122", "message": {"SQL":"\nSELECT\n\t\"BulkEmail\".\"Id\",\n\t\"BulkEmail\".\"CategoryId\",\n\t\"BulkEmail\".\"SendStartDate\",\n\t\"BulkEmail\".\"StatusId\",\n\t\"BulkEmail\".\"LaunchOptionId\"\nFROM\n\t\"public\".\"BulkEmail\"\n\tINNER JOIN \"public\".\"SendingEmailProgress\" ON (\"SendingEmailProgress\".\"BulkEmailId\" = \"BulkEmail\".\"Id\")\n\tLEFT OUTER JOIN \"public\".\"Campaign\" ON (\"Campaign\".\"Id\" = \"BulkEmail\".\"CampaignId\")\nWHERE\n\t\"BulkEmail\".\"StatusId\" IN (@P1, @P2, @P3, @P4, @P5)\n\tAND \"Campaign\".\"CampaignSchemaUId\" IS NULL\n\tAND \"SendingEmailProgress\".\"SendStartDate\" < @P6\n\tAND \"SendingEmailProgress\".\"SendStartDate\" > @P7","ErrorMessage":"42703: column SendingEmailProgress.SendStartDate does not exist","Parameters":[]} }
{ "time": "2023-11-23 19:42:00.2473", "level": "WARN", "app": "dotnet", "thread": "87", "message": {"SQL":"\nSELECT\n\t\"BulkEmail\".\"Id\",\n\t\"BulkEmail\".\"CategoryId\",\n\t\"BulkEmail\".\"SendStartDate\",\n\t\"BulkEmail\".\"StatusId\",\n\t\"BulkEmail\".\"LaunchOptionId\"\nFROM\n\t\"public\".\"BulkEmail\"\n\tINNER JOIN \"public\".\"SendingEmailProgress\" ON (\"SendingEmailProgress\".\"BulkEmailId\" = \"BulkEmail\".\"Id\")\n\tLEFT OUTER JOIN \"public\".\"Campaign\" ON (\"Campaign\".\"Id\" = \"BulkEmail\".\"CampaignId\")\nWHERE\n\t\"BulkEmail\".\"StatusId\" IN (@P1, @P2, @P3, @P4, @P5)\n\tAND \"Campaign\".\"CampaignSchemaUId\" IS NULL\n\tAND \"SendingEmailProgress\".\"SendStartDate\" < @P6\n\tAND \"SendingEmailProgress\".\"SendStartDate\" > @P7","ErrorMessage":"42703: column SendingEmailProgress.SendStartDate does not exist","Parameters":[]} }
{ "time": "2023-11-23 19:47:00.2466", "level": "WARN", "app": "dotnet", "thread": "111", "message": {"SQL":"\nSELECT\n\t\"BulkEmail\".\"Id\",\n\t\"BulkEmail\".\"CategoryId\",\n\t\"BulkEmail\".\"SendStartDate\",\n\t\"BulkEmail\".\"StatusId\",\n\t\"BulkEmail\".\"LaunchOptionId\"\nFROM\n\t\"public\".\"BulkEmail\"\n\tINNER JOIN \"public\".\"SendingEmailProgress\" ON (\"SendingEmailProgress\".\"BulkEmailId\" = \"BulkEmail\".\"Id\")\n\tLEFT OUTER JOIN \"public\".\"Campaign\" ON (\"Campaign\".\"Id\" = \"BulkEmail\".\"CampaignId\")\nWHERE\n\t\"BulkEmail\".\"StatusId\" IN (@P1, @P2, @P3, @P4, @P5)\n\tAND \"Campaign\".\"CampaignSchemaUId\" IS NULL\n\tAND \"SendingEmailProgress\".\"SendStartDate\" < @P6\n\tAND \"SendingEmailProgress\".\"SendStartDate\" > @P7","ErrorMessage":"42703: column SendingEmailProgress.SendStartDate does not exist","Parameters":[]} }
{ "time": "2023-11-23 19:52:00.2594", "level": "WARN", "app": "dotnet", "thread": "137", "message": {"SQL":"\nSELECT\n\t\"BulkEmail\".\"Id\",\n\t\"BulkEmail\".\"CategoryId\",\n\t\"BulkEmail\".\"SendStartDate\",\n\t\"BulkEmail\".\"StatusId\",\n\t\"BulkEmail\".\"LaunchOptionId\"\nFROM\n\t\"public\".\"BulkEmail\"\n\tINNER JOIN \"public\".\"SendingEmailProgress\" ON (\"SendingEmailProgress\".\"BulkEmailId\" = \"BulkEmail\".\"Id\")\n\tLEFT OUTER JOIN \"public\".\"Campaign\" ON (\"Campaign\".\"Id\" = \"BulkEmail\".\"CampaignId\")\nWHERE\n\t\"BulkEmail\".\"StatusId\" IN (@P1, @P2, @P3, @P4, @P5)\n\tAND \"Campaign\".\"CampaignSchemaUId\" IS NULL\n\tAND \"SendingEmailProgress\".\"SendStartDate\" < @P6\n\tAND \"SendingEmailProgress\".\"SendStartDate\" > @P7","ErrorMessage":"42703: column SendingEmailProgress.SendStartDate does not exist","Parameters":[]} }
{ "time": "2023-11-23 19:57:00.2471", "level": "WARN", "app": "dotnet", "thread": "97", "message": {"SQL":"\nSELECT\n\t\"BulkEmail\".\"Id\",\n\t\"BulkEmail\".\"CategoryId\",\n\t\"BulkEmail\".\"SendStartDate\",\n\t\"BulkEmail\".\"StatusId\",\n\t\"BulkEmail\".\"LaunchOptionId\"\nFROM\n\t\"public\".\"BulkEmail\"\n\tINNER JOIN \"public\".\"SendingEmailProgress\" ON (\"SendingEmailProgress\".\"BulkEmailId\" = \"BulkEmail\".\"Id\")\n\tLEFT OUTER JOIN \"public\".\"Campaign\" ON (\"Campaign\".\"Id\" = \"BulkEmail\".\"CampaignId\")\nWHERE\n\t\"BulkEmail\".\"StatusId\" IN (@P1, @P2, @P3, @P4, @P5)\n\tAND \"Campaign\".\"CampaignSchemaUId\" IS NULL\n\tAND \"SendingEmailProgress\".\"SendStartDate\" < @P6\n\tAND \"SendingEmailProgress\".\"SendStartDate\" > @P7","ErrorMessage":"42703: column SendingEmailProgress.SendStartDate does not exist","Parameters":[]} }
{ "time": "2023-11-23 20:02:00.2301", "level": "WARN", "app": "dotnet", "thread": "84", "message": {"SQL":"\nSELECT\n\t\"BulkEmail\".\"Id\",\n\t\"BulkEmail\".\"CategoryId\",\n\t\"BulkEmail\".\"SendStartDate\",\n\t\"BulkEmail\".\"StatusId\",\n\t\"BulkEmail\".\"LaunchOptionId\"\nFROM\n\t\"public\".\"BulkEmail\"\n\tINNER JOIN \"public\".\"SendingEmailProgress\" ON (\"SendingEmailProgress\".\"BulkEmailId\" = \"BulkEmail\".\"Id\")\n\tLEFT OUTER JOIN \"public\".\"Campaign\" ON (\"Campaign\".\"Id\" = \"BulkEmail\".\"CampaignId\")\nWHERE\n\t\"BulkEmail\".\"StatusId\" IN (@P1, @P2, @P3, @P4, @P5)\n\tAND \"Campaign\".\"CampaignSchemaUId\" IS NULL\n\tAND \"SendingEmailProgress\".\"SendStartDate\" < @P6\n\tAND \"SendingEmailProgress\".\"SendStartDate\" > @P7","ErrorMessage":"42703: column SendingEmailProgress.SendStartDate does not exist","Parameters":[]} }
{ "time": "2023-11-23 20:07:00.2650", "level": "WARN", "app": "dotnet", "thread": "132", "message": {"SQL":"\nSELECT\n\t\"BulkEmail\".\"Id\",\n\t\"BulkEmail\".\"CategoryId\",\n\t\"BulkEmail\".\"SendStartDate\",\n\t\"BulkEmail\".\"StatusId\",\n\t\"BulkEmail\".\"LaunchOptionId\"\nFROM\n\t\"public\".\"BulkEmail\"\n\tINNER JOIN \"public\".\"SendingEmailProgress\" ON (\"SendingEmailProgress\".\"BulkEmailId\" = \"BulkEmail\".\"Id\")\n\tLEFT OUTER JOIN \"public\".\"Campaign\" ON (\"Campaign\".\"Id\" = \"BulkEmail\".\"CampaignId\")\nWHERE\n\t\"BulkEmail\".\"StatusId\" IN (@P1, @P2, @P3, @P4, @P5)\n\tAND \"Campaign\".\"CampaignSchemaUId\" IS NULL\n\tAND \"SendingEmailProgress\".\"SendStartDate\" < @P6\n\tAND \"SendingEmailProgress\".\"SendStartDate\" > @P7","ErrorMessage":"42703: column SendingEmailProgress.SendStartDate does not exist","Parameters":[]} }
{ "time": "2023-11-23 20:12:00.2477", "level": "WARN", "app": "dotnet", "thread": "100", "message": {"SQL":"\nSELECT\n\t\"BulkEmail\".\"Id\",\n\t\"BulkEmail\".\"CategoryId\",\n\t\"BulkEmail\".\"SendStartDate\",\n\t\"BulkEmail\".\"StatusId\",\n\t\"BulkEmail\".\"LaunchOptionId\"\nFROM\n\t\"public\".\"BulkEmail\"\n\tINNER JOIN \"public\".\"SendingEmailProgress\" ON (\"SendingEmailProgress\".\"BulkEmailId\" = \"BulkEmail\".\"Id\")\n\tLEFT OUTER JOIN \"public\".\"Campaign\" ON (\"Campaign\".\"Id\" = \"BulkEmail\".\"CampaignId\")\nWHERE\n\t\"BulkEmail\".\"StatusId\" IN (@P1, @P2, @P3, @P4, @P5)\n\tAND \"Campaign\".\"CampaignSchemaUId\" IS NULL\n\tAND \"SendingEmailProgress\".\"SendStartDate\" < @P6\n\tAND \"SendingEmailProgress\".\"SendStartDate\" > @P7","ErrorMessage":"42703: column SendingEmailProgress.SendStartDate does not exist","Parameters":[]} }
{ "time": "2023-11-23 20:17:00.2304", "level": "WARN", "app": "dotnet", "thread": "112", "message": {"SQL":"\nSELECT\n\t\"BulkEmail\".\"Id\",\n\t\"BulkEmail\".\"CategoryId\",\n\t\"BulkEmail\".\"SendStartDate\",\n\t\"BulkEmail\".\"StatusId\",\n\t\"BulkEmail\".\"LaunchOptionId\"\nFROM\n\t\"public\".\"BulkEmail\"\n\tINNER JOIN \"public\".\"SendingEmailProgress\" ON (\"SendingEmailProgress\".\"BulkEmailId\" = \"BulkEmail\".\"Id\")\n\tLEFT OUTER JOIN \"public\".\"Campaign\" ON (\"Campaign\".\"Id\" = \"BulkEmail\".\"CampaignId\")\nWHERE\n\t\"BulkEmail\".\"StatusId\" IN (@P1, @P2, @P3, @P4, @P5)\n\tAND \"Campaign\".\"CampaignSchemaUId\" IS NULL\n\tAND \"SendingEmailProgress\".\"SendStartDate\" < @P6\n\tAND \"SendingEmailProgress\".\"SendStartDate\" > @P7","ErrorMessage":"42703: column SendingEmailProgress.SendStartDate does not exist","Parameters":[]} }
{ "time": "2023-11-23 20:22:00.2352", "level": "WARN", "app": "dotnet", "thread": "86", "message": {"SQL":"\nSELECT\n\t\"BulkEmail\".\"Id\",\n\t\"BulkEmail\".\"CategoryId\",\n\t\"BulkEmail\".\"SendStartDate\",\n\t\"BulkEmail\".\"StatusId\",\n\t\"BulkEmail\".\"LaunchOptionId\"\nFROM\n\t\"public\".\"BulkEmail\"\n\tINNER JOIN \"public\".\"SendingEmailProgress\" ON (\"SendingEmailProgress\".\"BulkEmailId\" = \"BulkEmail\".\"Id\")\n\tLEFT OUTER JOIN \"public\".\"Campaign\" ON (\"Campaign\".\"Id\" = \"BulkEmail\".\"CampaignId\")\nWHERE\n\t\"BulkEmail\".\"StatusId\" IN (@P1, @P2, @P3, @P4, @P5)\n\tAND \"Campaign\".\"CampaignSchemaUId\" IS NULL\n\tAND \"SendingEmailProgress\".\"SendStartDate\" < @P6\n\tAND \"SendingEmailProgress\".\"SendStartDate\" > @P7","ErrorMessage":"42703: column SendingEmailProgress.SendStartDate does not exist","Parameters":[]} }
{ "time": "2023-11-23 20:27:00.2384", "level": "WARN", "app": "dotnet", "thread": "129", "message": {"SQL":"\nSELECT\n\t\"BulkEmail\".\"Id\",\n\t\"BulkEmail\".\"CategoryId\",\n\t\"BulkEmail\".\"SendStartDate\",\n\t\"BulkEmail\".\"StatusId\",\n\t\"BulkEmail\".\"LaunchOptionId\"\nFROM\n\t\"public\".\"BulkEmail\"\n\tINNER JOIN \"public\".\"SendingEmailProgress\" ON (\"SendingEmailProgress\".\"BulkEmailId\" = \"BulkEmail\".\"Id\")\n\tLEFT OUTER JOIN \"public\".\"Campaign\" ON (\"Campaign\".\"Id\" = \"BulkEmail\".\"CampaignId\")\nWHERE\n\t\"BulkEmail\".\"StatusId\" IN (@P1, @P2, @P3, @P4, @P5)\n\tAND \"Campaign\".\"CampaignSchemaUId\" IS NULL\n\tAND \"SendingEmailProgress\".\"SendStartDate\" < @P6\n\tAND \"SendingEmailProgress\".\"SendStartDate\" > @P7","ErrorMessage":"42703: column SendingEmailProgress.SendStartDate does not exist","Parameters":[]} }
{ "time": "2023-11-23 20:32:00.2585", "level": "WARN", "app": "dotnet", "thread": "17", "message": {"SQL":"\nSELECT\n\t\"BulkEmail\".\"Id\",\n\t\"BulkEmail\".\"CategoryId\",\n\t\"BulkEmail\".\"SendStartDate\",\n\t\"BulkEmail\".\"StatusId\",\n\t\"BulkEmail\".\"LaunchOptionId\"\nFROM\n\t\"public\".\"BulkEmail\"\n\tINNER JOIN \"public\".\"SendingEmailProgress\" ON (\"SendingEmailProgress\".\"BulkEmailId\" = \"BulkEmail\".\"Id\")\n\tLEFT OUTER JOIN \"public\".\"Campaign\" ON (\"Campaign\".\"Id\" = \"BulkEmail\".\"CampaignId\")\nWHERE\n\t\"BulkEmail\".\"StatusId\" IN (@P1, @P2, @P3, @P4, @P5)\n\tAND \"Campaign\".\"CampaignSchemaUId\" IS NULL\n\tAND \"SendingEmailProgress\".\"SendStartDate\" < @P6\n\tAND \"SendingEmailProgress\".\"SendStartDate\" > @P7","ErrorMessage":"42703: column SendingEmailProgress.SendStartDate does not exist","Parameters":[]} }
{ "time": "2023-11-23 20:37:00.2503", "level": "WARN", "app": "dotnet", "thread": "113", "message": {"SQL":"\nSELECT\n\t\"BulkEmail\".\"Id\",\n\t\"BulkEmail\".\"CategoryId\",\n\t\"BulkEmail\".\"SendStartDate\",\n\t\"BulkEmail\".\"StatusId\",\n\t\"BulkEmail\".\"LaunchOptionId\"\nFROM\n\t\"public\".\"BulkEmail\"\n\tINNER JOIN \"public\".\"SendingEmailProgress\" ON (\"SendingEmailProgress\".\"BulkEmailId\" = \"BulkEmail\".\"Id\")\n\tLEFT OUTER JOIN \"public\".\"Campaign\" ON (\"Campaign\".\"Id\" = \"BulkEmail\".\"CampaignId\")\nWHERE\n\t\"BulkEmail\".\"StatusId\" IN (@P1, @P2, @P3, @P4, @P5)\n\tAND \"Campaign\".\"CampaignSchemaUId\" IS NULL\n\tAND \"SendingEmailProgress\".\"SendStartDate\" < @P6\n\tAND \"SendingEmailProgress\".\"SendStartDate\" > @P7","ErrorMessage":"42703: column SendingEmailProgress.SendStartDate does not exist","Parameters":[]} }
{ "time": "2023-11-23 20:42:00.2384", "level": "WARN", "app": "dotnet", "thread": "113", "message": {"SQL":"\nSELECT\n\t\"BulkEmail\".\"Id\",\n\t\"BulkEmail\".\"CategoryId\",\n\t\"BulkEmail\".\"SendStartDate\",\n\t\"BulkEmail\".\"StatusId\",\n\t\"BulkEmail\".\"LaunchOptionId\"\nFROM\n\t\"public\".\"BulkEmail\"\n\tINNER JOIN \"public\".\"SendingEmailProgress\" ON (\"SendingEmailProgress\".\"BulkEmailId\" = \"BulkEmail\".\"Id\")\n\tLEFT OUTER JOIN \"public\".\"Campaign\" ON (\"Campaign\".\"Id\" = \"BulkEmail\".\"CampaignId\")\nWHERE\n\t\"BulkEmail\".\"StatusId\" IN (@P1, @P2, @P3, @P4, @P5)\n\tAND \"Campaign\".\"CampaignSchemaUId\" IS NULL\n\tAND \"SendingEmailProgress\".\"SendStartDate\" < @P6\n\tAND \"SendingEmailProgress\".\"SendStartDate\" > @P7","ErrorMessage":"42703: column SendingEmailProgress.SendStartDate does not exist","Parameters":[]} }
